tornado_swagger/__init__.py
tornado_swagger/builders.py
tornado_swagger/components.py
tornado_swagger/handlers.py
tornado_swagger/setup.py
tornado_swagger/swagger_ui/ui.jinja2
tornado_swagger/templates/swagger.yaml
tornado_rest_swagger-1.2.1.dist-info/LICENSE
tornado_rest_swagger-1.2.1.dist-info/METADATA
tornado_rest_swagger-1.2.1.dist-info/WHEEL
tornado_rest_swagger-1.2.1.dist-info/top_level.txt
tornado_rest_swagger-1.2.1.dist-info/RECORD
