Metadata-Version: 2.1
Name: tornado-rest-swagger
Version: 1.2.1
Summary: Swagger API Documentation builder for tornado server
Home-page: https://github.com/Cluas/tornado-rest-swagger
Author: Cluas Alex
Author-email: Cluas@live.cn
License: MIT License
Download-URL: https://pypi.org/project/tornado-rest-swagger/#files
Platform: UNKNOWN
Classifier: Intended Audience :: System Administrators
Classifier: License :: OSI Approved :: MIT License
Classifier: Operating System :: OS Independent
Classifier: Programming Language :: Python
Classifier: Programming Language :: Python :: 2.7
Classifier: Programming Language :: Python :: 3.4
Classifier: Programming Language :: Python :: 3.5
Classifier: Programming Language :: Python :: 3.6
Classifier: Programming Language :: Python :: 3.7
Classifier: Topic :: Software Development :: Libraries :: Python Modules
